PIL/MpoImagePlugin.py
PIL/ImageMode.py
PIL/PngImagePlugin.py
PIL/_imagingmorph.cpython-310-darwin.so
PIL/XbmImagePlugin.py
PIL/PcxImagePlugin.py
PIL/SunImagePlugin.py
PIL/ImageFile.py
PIL/SpiderImagePlugin.py
PIL/_imagingtk.cpython-310-darwin.so
PIL/TarIO.py
PIL/FitsStubImagePlugin.py
PIL/MpegImagePlugin.py
PIL/BdfFontFile.py
PIL/GribStubImagePlugin.py
PIL/ImageStat.py
PIL/PixarImagePlugin.py
PIL/GimpPaletteFile.py
PIL/ImageColor.py
PIL/ContainerIO.py
PIL/MspImagePlugin.py
PIL/MicImagePlugin.py
PIL/_version.py
PIL/ImtImagePlugin.py
PIL/GifImagePlugin.py
PIL/PalmImagePlugin.py
PIL/ImageQt.py
PIL/ImageMath.py
PIL/PaletteFile.py
PIL/FontFile.py
PIL/PdfParser.py
PIL/ExifTags.py
PIL/ImageCms.py
PIL/FpxImagePlugin.py
PIL/ImageChops.py
PIL/_deprecate.py
PIL/BufrStubImagePlugin.py
PIL/PSDraw.py
PIL/PcdImagePlugin.py
PIL/ImageFilter.py
PIL/ImageDraw2.py
PIL/ImagePath.py
PIL/DcxImagePlugin.py
PIL/__init__.py
PIL/JpegPresets.py
PIL/Hdf5StubImagePlugin.py
PIL/features.py
PIL/ImageDraw.py
PIL/GimpGradientFile.py
PIL/ImageWin.py
PIL/IcoImagePlugin.py
PIL/_tkinter_finder.py
PIL/EpsImagePlugin.py
PIL/TgaImagePlugin.py
PIL/ImageMorph.py
PIL/Jpeg2KImagePlugin.py
PIL/WalImageFile.py
PIL/PcfFontFile.py
PIL/BlpImagePlugin.py
PIL/ImageTk.py
PIL/GbrImagePlugin.py
PIL/ImageOps.py
PIL/_webp.cpython-310-darwin.so
PIL/PdfImagePlugin.py
PIL/ImageShow.py
PIL/ImageEnhance.py
PIL/WmfImagePlugin.py
PIL/ImageGrab.py
PIL/_imagingft.cpython-310-darwin.so
PIL/WebPImagePlugin.py
PIL/FliImagePlugin.py
PIL/TiffTags.py
PIL/CurImagePlugin.py
PIL/_util.py
PIL/_imagingcms.cpython-310-darwin.so
PIL/GdImageFile.py
PIL/TiffImagePlugin.py
PIL/IptcImagePlugin.py
PIL/ImagePalette.py
PIL/BmpImagePlugin.py
PIL/ImageTransform.py
PIL/IcnsImagePlugin.py
PIL/McIdasImagePlugin.py
PIL/FitsImagePlugin.py
PIL/XpmImagePlugin.py
PIL/DdsImagePlugin.py
PIL/ImageSequence.py
PIL/_imagingmath.cpython-310-darwin.so
PIL/PyAccess.py
Pillow-9.2.0.dist-info/zip-safe
Pillow-9.2.0.dist-info/RECORD
Pillow-9.2.0.dist-info/LICENSE
Pillow-9.2.0.dist-info/WHEEL
Pillow-9.2.0.dist-info/top_level.txt
Pillow-9.2.0.dist-info/METADATA
