Metadata-Version: 2.1
Name: Pillow
Version: 9.2.0
Summary: Python Imaging Library (Fork)
Home-page: https://python-pillow.org
Author: Alex Clark (PIL Fork Author)
Author-email: aclark@python-pillow.org
License: HPND
Project-URL: Documentation, https://pillow.readthedocs.io
Project-URL: Source, https://github.com/python-pillow/Pillow
Project-URL: Funding, https://tidelift.com/subscription/pkg/pypi-pillow?utm_source=pypi-pillow&utm_medium=pypi
Project-URL: Release notes, https://pillow.readthedocs.io/en/stable/releasenotes/index.html
Project-URL: Changelog, https://github.com/python-pillow/Pillow/blob/main/CHANGES.rst
Project-URL: Twitter, https://twitter.com/PythonPillow
Keywords: Imaging
Classifier: Development Status :: 6 - Mature
Classifier: License :: OSI Approved :: Historical Permission Notice and Disclaimer (HPND)
Classifier: Programming Language :: Python :: 3
Classifier: Programming Language :: Python :: 3 :: Only
Classifier: Programming Language :: Python :: 3.7
Classifier: Programming Language :: Python :: 3.8
Classifier: Programming Language :: Python :: 3.9
Classifier: Programming Language :: Python :: 3.10
Classifier: Programming Language :: Python :: Implementation :: CPython
Classifier: Programming Language :: Python :: Implementation :: PyPy
Classifier: Topic :: Multimedia :: Graphics
Classifier: Topic :: Multimedia :: Graphics :: Capture :: Digital Camera
Classifier: Topic :: Multimedia :: Graphics :: Capture :: Screen Capture
Classifier: Topic :: Multimedia :: Graphics :: Graphics Conversion
Classifier: Topic :: Multimedia :: Graphics :: Viewers
Requires-Python: >=3.7
Provides-Extra: docs
Provides-Extra: tests
License-File: LICENSE
